tffpy/__init__.py
tffpy/create_subregions.py
tffpy/datasets.py
tffpy/interpolation_solver.py
tffpy/tf_fading.py
tffpy/tf_tools.py
tffpy/utils.py
tffpy/experiments/__init__.py
tffpy/experiments/exp_solve_tff.py
tffpy/experiments/exp_variance.py
tffpy/experiments/yafe_slurm.py
tffpy/tests/__init__.py
tffpy/tests/ci_config.py
tffpy/tests/test_create_subregions.py
tffpy/tests/test_datasets.py
tffpy/tests/test_interpolation_solver.py
tffpy/tests/test_tf_fading.py
tffpy/tests/test_utils.py
tffpy/unversioned/__init__.py
tffpy/unversioned/script_extract_ranks_masksize.py
tffpy/unversioned/script_extract_ranks_masksize_nodep.py
tffpy/unversioned/script_mask_bird_car.py
tffpy/unversioned/slurm.py
tffpy-0.1.5.dist-info/DESCRIPTION.rst
tffpy-0.1.5.dist-info/METADATA
tffpy-0.1.5.dist-info/RECORD
tffpy-0.1.5.dist-info/WHEEL
tffpy-0.1.5.dist-info/metadata.json
tffpy-0.1.5.dist-info/top_level.txt
