Metadata-Version: 2.0
Name: tffpy
Version: 0.1.5
Summary: Time frequency fading using Gabor multipliers
Home-page: https://gitlab.lis-lab.fr/skmad-suite/tff2020
Author: Valentin Emiya, Ama Marina Kreme
Author-email: valentin.emiya@lis-lab.fr, ama-marina.kreme@lis-lab.fr
License: GNU General Public License v3 (GPLv3)
Keywords: time-frequency,fading,filtering,Gabor multiplier,audio
Platform: UNKNOWN
Classifier: Development Status :: 5 - Production/Stable
Classifier: Intended Audience :: Developers
Classifier: Intended Audience :: End Users/Desktop
Classifier: Intended Audience :: Science/Research
Classifier: Topic :: Scientific/Engineering :: Mathematics
Classifier: License :: OSI Approved :: GNU General Public License v3 (GPLv3)
Classifier: Natural Language :: English
Classifier: Operating System :: MacOS :: MacOS X 
Classifier: Operating System :: POSIX :: Linux
Classifier: Programming Language :: Python :: 3.6
Requires-Python: >=3.6
Requires-Dist: ltfatpy
Requires-Dist: madarrays
Requires-Dist: matplotlib
Requires-Dist: numpy
Requires-Dist: pandas
Requires-Dist: scipy
Requires-Dist: skpomade
Requires-Dist: xarray
Requires-Dist: yafe
Provides-Extra: dev
Requires-Dist: coverage; extra == 'dev'
Requires-Dist: pytest; extra == 'dev'
Requires-Dist: pytest-cov; extra == 'dev'
Requires-Dist: pytest-randomly; extra == 'dev'
Provides-Extra: doc
Requires-Dist: nbsphinx; extra == 'doc'
Requires-Dist: numpydoc; extra == 'doc'
Requires-Dist: sphinx; extra == 'doc'
